pimg/__init__.py
pimg/main.py
pimg/pimg.py
pimg/py.typed
pimg-0.1.1.dist-info/LICENSE
pimg-0.1.1.dist-info/METADATA
pimg-0.1.1.dist-info/WHEEL
pimg-0.1.1.dist-info/entry_points.txt
pimg-0.1.1.dist-info/top_level.txt
pimg-0.1.1.dist-info/RECORD
